MANIFEST.in
README.rst
setup.py
slurchemy/README.rst
slurchemy/__init__.py
slurchemy/reflect.py
slurchemy/utils.py
slurchemy.egg-info/PKG-INFO
slurchemy.egg-info/SOURCES.txt
slurchemy.egg-info/dependency_links.txt
slurchemy.egg-info/entry_points.txt
slurchemy.egg-info/not-zip-safe
slurchemy.egg-info/requires.txt
slurchemy.egg-info/top_level.txt