Metadata-Version: 1.0
Name: slurchemy
Version: 0.2.6
Summary: SQLAlchemy bindings for your slurmdbd (SLURM database)
Home-page: http://github.com/ralphbean/slurchemy
Author: Ralph Bean
Author-email: ralph.bean@gmail.com
License: GPLv3+
Keywords: slurm slurmdbd sqlalchemy
Platform: UNKNOWN
Classifier: Intended Audience :: Developers
Classifier: Intended Audience :: System Administrators
Classifier: Development Status :: 2 - Pre-Alpha
Classifier: License :: OSI Approved :: GNU General Public License (GPL)
Classifier: Programming Language :: Python :: 2
Classifier: Topic :: Database
Classifier: Topic :: System :: Clustering
Classifier: Topic :: System :: Distributed Computing
